setup.py
appointmentguru/__init__.py
appointmentguru/communicationguru.py
appointmentguru/endpoints.py
appointmentguru/mixins.py
appointmentguru/test_communicationguru.py
appointmentguru_helpers.egg-info/PKG-INFO
appointmentguru_helpers.egg-info/SOURCES.txt
appointmentguru_helpers.egg-info/dependency_links.txt
appointmentguru_helpers.egg-info/not-zip-safe
appointmentguru_helpers.egg-info/top_level.txt