Metadata-Version: 1.0
Name: appointmentguru-helpers
Version: 0.3
Summary: General purpose utilities for AppointmentGuru microservices
Home-page: https://github.com/AppointmentGuru/AppointmentGuruMicroServiceLib
Author: Christo Crampton
Author-email: tech@appointmentguru.co
License: MIT
Platform: UNKNOWN
